joypad/__init__.py
joypad/controller.py
joypad/pyglet_controls.py
joypad-0.0.4.dist-info/METADATA
joypad-0.0.4.dist-info/WHEEL
joypad-0.0.4.dist-info/licenses/LICENSE.txt
joypad-0.0.4.dist-info/RECORD
