Metadata-Version: 2.4
Name: joypad
Version: 0.0.4
Summary: Control apps with standard dual-joystick controllers.
Author-email: "Nicholas A. Del Grosso" <delgrosso.nick@gmail.com>
Maintainer-email: "Nicholas A. Del Grosso" <delgrosso.nick@gmail.com>
License-Expression: MIT
License-File: LICENSE.txt
Keywords: controller,gaming,joystick
Requires-Python: >=3.7
Requires-Dist: pyglet>=2.1
